pillowstrap/__init__.py
pillowstrap/theme.py
pillowstrap-1.0.2.dist-info/licenses/LICENSE
pillowstrap-1.0.2.dist-info/METADATA
pillowstrap-1.0.2.dist-info/WHEEL
pillowstrap-1.0.2.dist-info/top_level.txt
pillowstrap-1.0.2.dist-info/RECORD
