Metadata-Version: 2.4
Name: pillowstrap
Version: 1.0.2
Summary: A Bootstrap-like semantic wrapper for Python Pillow
Home-page: https://github.com/rnclvr13/
Author: Clever
Author-email: clevermonteros@gmail.com
Classifier: Programming Language :: Python :: 3
Classifier: License :: OSI Approved :: MIT License
Classifier: Operating System :: OS Independent
Requires-Python: >=3.6
License-File: LICENSE
Requires-Dist: Pillow>=10.0.0
Dynamic: author
Dynamic: author-email
Dynamic: classifier
Dynamic: description
Dynamic: description-content-type
Dynamic: home-page
Dynamic: license-file
Dynamic: requires-dist
Dynamic: requires-python
Dynamic: summary
